django_view_permissions/__init__.py
django_view_permissions/access.py
django_view_permissions/middleware.py
django_view_permissions/tests/__init__.py
django_view_permissions/tests/test_middleware.py
django_view_permissions/tests/test_app/__init__.py
django_view_permissions/tests/test_app/permissions.py
django_view_permissions/tests/test_app/urls.py
django_view_permissions/tests/test_app/views.py
django_view_permissions-0.0.2.dist-info/LICENSE
django_view_permissions-0.0.2.dist-info/METADATA
django_view_permissions-0.0.2.dist-info/WHEEL
django_view_permissions-0.0.2.dist-info/top_level.txt
django_view_permissions-0.0.2.dist-info/RECORD
